[
  {
    "SpeciesCode": "SI18-15",
    "taxon": "Piloderma sphaerosporum",
    "snamn": "Saknar svenskt namn",
    "matsvamp": 0,
    "total_presence": 199,
    "Artfakta": "https://artfakta.se/artinformation/taxa/253758/detaljer",
    "RL2020kat": "LC",
    "Svamp-grupp": "skinnsvamp",
    "Svamp-Undersvamp-grupp": "0",
    "SIGNAL_art": "0",
    "Svampguiden": "0",
    "Nya svamp-boken": "0",
    "Genus": "Piloderma",
    "sample_plot_count": 5,
    "sample_env_count": 5,
    "Svamp-grupp-släkte": "skinnsvamp"
  },
  {
    "SpeciesCode": "SI18-24",
    "taxon": "Hyaloscypha variabilis",
    "snamn": "Saknar svenskt namn",
    "matsvamp": 0,
    "total_presence": 123,
    "Artfakta": "Information saknas",
    "RL2020kat": "0",
    "Svamp-grupp": "0",
    "Svamp-Undersvamp-grupp": "0",
    "SIGNAL_art": "0",
    "Svampguiden": "0",
    "Nya svamp-boken": "0",
    "Genus": "Hyaloscypha",
    "sample_plot_count": 5,
    "sample_env_count": 5,
    "Svamp-grupp-släkte": "skålsvamp"
  },
  {
    "SpeciesCode": "SI18-4",
    "taxon": "Cenococcum geophilum (coll.) sp.3",
    "snamn": "Saknar svenskt namn",
    "matsvamp": 0,
    "total_presence": 156,
    "Artfakta": "Information saknas",
    "RL2020kat": "0",
    "Svamp-grupp": "0",
    "Svamp-Undersvamp-grupp": "0",
    "SIGNAL_art": "0",
    "Svampguiden": "0",
    "Nya svamp-boken": "0",
    "Genus": "Cenococcum",
    "sample_plot_count": 4,
    "sample_env_count": 5,
    "Svamp-grupp-släkte": "övrigt"
  },
  {
    "SpeciesCode": "SI18-10",
    "taxon": "Tylospora fibrillosa",
    "snamn": "bomullsskinn",
    "matsvamp": 0,
    "total_presence": 191,
    "Artfakta": "https://artfakta.se/artinformation/taxa/6347/detaljer",
    "RL2020kat": "LC",
    "Svamp-grupp": "skinnsvamp",
    "Svamp-Undersvamp-grupp": "0",
    "SIGNAL_art": "0",
    "Svampguiden": "0",
    "Nya svamp-boken": "0",
    "Genus": "Tylospora",
    "sample_plot_count": 3,
    "sample_env_count": 5,
    "Svamp-grupp-släkte": "skinnsvamp"
  },
  {
    "SpeciesCode": "SI18-26",
    "taxon": "Hyaloscypha finlandica sp.1",
    "snamn": "Saknar svenskt namn",
    "matsvamp": 0,
    "total_presence": 9,
    "Artfakta": "Information saknas",
    "RL2020kat": "0",
    "Svamp-grupp": "0",
    "Svamp-Undersvamp-grupp": "0",
    "SIGNAL_art": "0",
    "Svampguiden": "0",
    "Nya svamp-boken": "0",
    "Genus": "Hyaloscypha",
    "sample_plot_count": 3,
    "sample_env_count": 5,
    "Svamp-grupp-släkte": "skålsvamp"
  },
  {
    "SpeciesCode": "SI18-31",
    "taxon": "Piloderma olivaceum sp.1",
    "snamn": "mörkt ullskinn",
    "matsvamp": 0,
    "total_presence": 66,
    "Artfakta": "https://artfakta.se/artinformation/taxa/5548/detaljer",
    "RL2020kat": "LC",
    "Svamp-grupp": "skinnsvamp",
    "Svamp-Undersvamp-grupp": "0",
    "SIGNAL_art": "0",
    "Svampguiden": "0",
    "Nya svamp-boken": "0",
    "Genus": "Piloderma",
    "sample_plot_count": 3,
    "sample_env_count": 5,
    "Svamp-grupp-släkte": "skinnsvamp"
  },
  {
    "SpeciesCode": "SI18-127",
    "taxon": "Suillus bovinus",
    "snamn": "örsopp",
    "matsvamp": 1,
    "total_presence": 4,
    "Artfakta": "https://artfakta.se/artinformation/taxa/6084/detaljer",
    "RL2020kat": "LC",
    "Svamp-grupp": "sopp",
    "Svamp-Undersvamp-grupp": "0",
    "SIGNAL_art": "0",
    "Svampguiden": "https://svampguiden.com/art/visa/suillus_bovinus",
    "Nya svamp-boken": "x",
    "Genus": "Suillus",
    "sample_plot_count": 2,
    "sample_env_count": 5,
    "Svamp-grupp-släkte": "sopp"
  },
  {
    "SpeciesCode": "SI18-274",
    "taxon": "Thelephora alnii",
    "snamn": "Saknar svenskt namn",
    "matsvamp": 0,
    "total_presence": 28,
    "Artfakta": "Information saknas",
    "RL2020kat": "0",
    "Svamp-grupp": "0",
    "Svamp-Undersvamp-grupp": "0",
    "SIGNAL_art": "0",
    "Svampguiden": "0",
    "Nya svamp-boken": "0",
    "Genus": "Thelephora",
    "sample_plot_count": 2,
    "sample_env_count": 5,
    "Svamp-grupp-släkte": "skinnsvamp"
  },
  {
    "SpeciesCode": "SI18-28",
    "taxon": "Russula decolorans",
    "snamn": "tegelkremla",
    "matsvamp": 1,
    "total_presence": 12,
    "Artfakta": "https://artfakta.se/artinformation/taxa/5852/detaljer",
    "RL2020kat": "LC",
    "Svamp-grupp": "hattsvamp",
    "Svamp-Undersvamp-grupp": "0",
    "SIGNAL_art": "0",
    "Svampguiden": "https://svampguiden.com/art/visa/russula_decolorans",
    "Nya svamp-boken": "x",
    "Genus": "Russula",
    "sample_plot_count": 2,
    "sample_env_count": 5,
    "Svamp-grupp-släkte": "hattsvamp"
  },
  {
    "SpeciesCode": "SI18-48",
    "taxon": "Russula paludosa",
    "snamn": "storkremla",
    "matsvamp": 1,
    "total_presence": 2,
    "Artfakta": "https://artfakta.se/artinformation/taxa/5908/detaljer",
    "RL2020kat": "LC",
    "Svamp-grupp": "hattsvamp",
    "Svamp-Undersvamp-grupp": "0",
    "SIGNAL_art": "0",
    "Svampguiden": "https://svampguiden.com/art/visa/russula_paludosa",
    "Nya svamp-boken": "x",
    "Genus": "Russula",
    "sample_plot_count": 2,
    "sample_env_count": 5,
    "Svamp-grupp-släkte": "hattsvamp"
  },
  {
    "SpeciesCode": "SI18-54",
    "taxon": "Cortinarius armillatus",
    "snamn": "rödbandad spindling",
    "matsvamp": 0,
    "total_presence": 258,
    "Artfakta": "https://artfakta.se/artinformation/taxa/3541/detaljer",
    "RL2020kat": "LC",
    "Svamp-grupp": "hattsvamp",
    "Svamp-Undersvamp-grupp": "0",
    "SIGNAL_art": "0",
    "Svampguiden": "0",
    "Nya svamp-boken": "0",
    "Genus": "Cortinarius",
    "sample_plot_count": 2,
    "sample_env_count": 5,
    "Svamp-grupp-släkte": "hattsvamp"
  },
  {
    "SpeciesCode": "SI18-58",
    "taxon": "Piloderma olivaceum sp.2",
    "snamn": "mörkt ullskinn",
    "matsvamp": 0,
    "total_presence": 229,
    "Artfakta": "https://artfakta.se/artinformation/taxa/5548/detaljer",
    "RL2020kat": "LC",
    "Svamp-grupp": "skinnsvamp",
    "Svamp-Undersvamp-grupp": "0",
    "SIGNAL_art": "0",
    "Svampguiden": "0",
    "Nya svamp-boken": "0",
    "Genus": "Piloderma",
    "sample_plot_count": 2,
    "sample_env_count": 5,
    "Svamp-grupp-släkte": "skinnsvamp"
  },
  {
    "SpeciesCode": "SI18-85",
    "taxon": "Amanita fulva",
    "snamn": "brun kamskivling",
    "matsvamp": 0,
    "total_presence": 41,
    "Artfakta": "https://artfakta.se/artinformation/taxa/2974/detaljer",
    "RL2020kat": "LC",
    "Svamp-grupp": "hattsvamp",
    "Svamp-Undersvamp-grupp": "0",
    "SIGNAL_art": "0",
    "Svampguiden": "0",
    "Nya svamp-boken": "0",
    "Genus": "Amanita",
    "sample_plot_count": 2,
    "sample_env_count": 5,
    "Svamp-grupp-släkte": "hattsvamp"
  },
  {
    "SpeciesCode": "SI18-90",
    "taxon": "Polyozellus umbrinus",
    "snamn": "Saknar svenskt namn",
    "matsvamp": 0,
    "total_presence": 8,
    "Artfakta": "https://artfakta.se/artinformation/taxa/6040133/detaljer",
    "RL2020kat": "LC",
    "Svamp-grupp": "skinnsvamp",
    "Svamp-Undersvamp-grupp": "0",
    "SIGNAL_art": "0",
    "Svampguiden": "0",
    "Nya svamp-boken": "0",
    "Genus": "Polyozellus",
    "sample_plot_count": 2,
    "sample_env_count": 5,
    "Svamp-grupp-släkte": "Saknas"
  },
  {
    "SpeciesCode": "SI18-1001",
    "taxon": "Cortinarius diasemospermus var. leptospermus sp.1",
    "snamn": "Saknar svenskt namn",
    "matsvamp": 0,
    "total_presence": 4,
    "Artfakta": "https://artfakta.se/artinformation/taxa/249319/detaljer",
    "RL2020kat": "NE",
    "Svamp-grupp": "hattsvamp",
    "Svamp-Undersvamp-grupp": "0",
    "SIGNAL_art": "0",
    "Svampguiden": "0",
    "Nya svamp-boken": "0",
    "Genus": "Cortinarius",
    "sample_plot_count": 1,
    "sample_env_count": 5,
    "Svamp-grupp-släkte": "hattsvamp"
  },
  {
    "SpeciesCode": "SI18-120",
    "taxon": "Thelephora terrestris",
    "snamn": "vårtöra",
    "matsvamp": 0,
    "total_presence": 1,
    "Artfakta": "https://artfakta.se/artinformation/taxa/6155/detaljer",
    "RL2020kat": "LC",
    "Svamp-grupp": "skinnsvamp",
    "Svamp-Undersvamp-grupp": "0",
    "SIGNAL_art": "0",
    "Svampguiden": "0",
    "Nya svamp-boken": "0",
    "Genus": "Thelephora",
    "sample_plot_count": 1,
    "sample_env_count": 5,
    "Svamp-grupp-släkte": "skinnsvamp"
  },
  {
    "SpeciesCode": "SI18-130",
    "taxon": "Cortinarius kauffmanianus",
    "snamn": "Saknar svenskt namn",
    "matsvamp": 0,
    "total_presence": 1,
    "Artfakta": "Information saknas",
    "RL2020kat": "0",
    "Svamp-grupp": "0",
    "Svamp-Undersvamp-grupp": "0",
    "SIGNAL_art": "0",
    "Svampguiden": "0",
    "Nya svamp-boken": "0",
    "Genus": "Cortinarius",
    "sample_plot_count": 1,
    "sample_env_count": 5,
    "Svamp-grupp-släkte": "hattsvamp"
  },
  {
    "SpeciesCode": "SI18-141",
    "taxon": "Tomentellopsis echinospora sp.1",
    "snamn": "brunt brokskinn",
    "matsvamp": 0,
    "total_presence": 3,
    "Artfakta": "https://artfakta.se/artinformation/taxa/6185/detaljer",
    "RL2020kat": "LC",
    "Svamp-grupp": "skinnsvamp",
    "Svamp-Undersvamp-grupp": "0",
    "SIGNAL_art": "0",
    "Svampguiden": "0",
    "Nya svamp-boken": "0",
    "Genus": "Tomentellopsis",
    "sample_plot_count": 1,
    "sample_env_count": 5,
    "Svamp-grupp-släkte": "skinnsvamp"
  },
  {
    "SpeciesCode": "SI18-153",
    "taxon": "Lactarius vietus/pilatii",
    "snamn": "Saknar svenskt namn",
    "matsvamp": 0,
    "total_presence": 1,
    "Artfakta": "Information saknas",
    "RL2020kat": "0",
    "Svamp-grupp": "0",
    "Svamp-Undersvamp-grupp": "0",
    "SIGNAL_art": "0",
    "Svampguiden": "0",
    "Nya svamp-boken": "0",
    "Genus": "Lactarius",
    "sample_plot_count": 1,
    "sample_env_count": 5,
    "Svamp-grupp-släkte": "hattsvamp"
  },
  {
    "SpeciesCode": "SI18-214",
    "taxon": "Russula emetica (coll.) - betularum",
    "snamn": "Saknar svenskt namn",
    "matsvamp": 0,
    "total_presence": 7,
    "Artfakta": "Information saknas",
    "RL2020kat": "0",
    "Svamp-grupp": "0",
    "Svamp-Undersvamp-grupp": "0",
    "SIGNAL_art": "0",
    "Svampguiden": "0",
    "Nya svamp-boken": "0",
    "Genus": "Russula",
    "sample_plot_count": 1,
    "sample_env_count": 5,
    "Svamp-grupp-släkte": "hattsvamp"
  },
  {
    "SpeciesCode": "SI18-217",
    "taxon": "Polyozellus humicola",
    "snamn": "Saknar svenskt namn",
    "matsvamp": 0,
    "total_presence": 2,
    "Artfakta": "https://artfakta.se/artinformation/taxa/6046595/detaljer",
    "RL2020kat": "NE",
    "Svamp-grupp": "skinnsvamp",
    "Svamp-Undersvamp-grupp": "0",
    "SIGNAL_art": "0",
    "Svampguiden": "0",
    "Nya svamp-boken": "0",
    "Genus": "Polyozellus",
    "sample_plot_count": 1,
    "sample_env_count": 5,
    "Svamp-grupp-släkte": "Saknas"
  },
  {
    "SpeciesCode": "SI18-30",
    "taxon": "Lactarius rufus",
    "snamn": "pepparriska",
    "matsvamp": 1,
    "total_presence": 1,
    "Artfakta": "https://artfakta.se/artinformation/taxa/4763/detaljer",
    "RL2020kat": "LC",
    "Svamp-grupp": "hattsvamp",
    "Svamp-Undersvamp-grupp": "0",
    "SIGNAL_art": "0",
    "Svampguiden": "https://svampguiden.com/art/visa/lactarius_rufus",
    "Nya svamp-boken": "x",
    "Genus": "Lactarius",
    "sample_plot_count": 1,
    "sample_env_count": 5,
    "Svamp-grupp-släkte": "hattsvamp"
  },
  {
    "SpeciesCode": "SI18-38",
    "taxon": "Cortinarius aurae",
    "snamn": "Saknar svenskt namn",
    "matsvamp": 0,
    "total_presence": 10,
    "Artfakta": "Information saknas",
    "RL2020kat": "0",
    "Svamp-grupp": "0",
    "Svamp-Undersvamp-grupp": "0",
    "SIGNAL_art": "0",
    "Svampguiden": "0",
    "Nya svamp-boken": "0",
    "Genus": "Cortinarius",
    "sample_plot_count": 1,
    "sample_env_count": 5,
    "Svamp-grupp-släkte": "hattsvamp"
  },
  {
    "SpeciesCode": "SI18-396",
    "taxon": "Cortinarius pholideus",
    "snamn": "tofsspindling",
    "matsvamp": 0,
    "total_presence": 1,
    "Artfakta": "https://artfakta.se/artinformation/taxa/3687/detaljer",
    "RL2020kat": "LC",
    "Svamp-grupp": "hattsvamp",
    "Svamp-Undersvamp-grupp": "0",
    "SIGNAL_art": "0",
    "Svampguiden": "0",
    "Nya svamp-boken": "0",
    "Genus": "Cortinarius",
    "sample_plot_count": 1,
    "sample_env_count": 5,
    "Svamp-grupp-släkte": "hattsvamp"
  },
  {
    "SpeciesCode": "SI18-402",
    "taxon": "Hebeloma velutipes (coll.) sp.2",
    "snamn": "Saknar svenskt namn",
    "matsvamp": 0,
    "total_presence": 5,
    "Artfakta": "Information saknas",
    "RL2020kat": "0",
    "Svamp-grupp": "0",
    "Svamp-Undersvamp-grupp": "0",
    "SIGNAL_art": "0",
    "Svampguiden": "0",
    "Nya svamp-boken": "0",
    "Genus": "Hebeloma",
    "sample_plot_count": 1,
    "sample_env_count": 5,
    "Svamp-grupp-släkte": "hattsvamp"
  },
  {
    "SpeciesCode": "SI18-430",
    "taxon": "Chalciporus piperatus",
    "snamn": "Saknar svenskt namn",
    "matsvamp": 0,
    "total_presence": 1,
    "Artfakta": "Information saknas",
    "RL2020kat": "0",
    "Svamp-grupp": "0",
    "Svamp-Undersvamp-grupp": "0",
    "SIGNAL_art": "0",
    "Svampguiden": "0",
    "Nya svamp-boken": "0",
    "Genus": "Chalciporus",
    "sample_plot_count": 1,
    "sample_env_count": 5,
    "Svamp-grupp-släkte": "sopp"
  },
  {
    "SpeciesCode": "SI18-49",
    "taxon": "Piloderma bicolor",
    "snamn": "Saknar svenskt namn",
    "matsvamp": 0,
    "total_presence": 1,
    "Artfakta": "Information saknas",
    "RL2020kat": "0",
    "Svamp-grupp": "0",
    "Svamp-Undersvamp-grupp": "0",
    "SIGNAL_art": "0",
    "Svampguiden": "0",
    "Nya svamp-boken": "0",
    "Genus": "Piloderma",
    "sample_plot_count": 1,
    "sample_env_count": 5,
    "Svamp-grupp-släkte": "skinnsvamp"
  },
  {
    "SpeciesCode": "SI18-638",
    "taxon": "Thaxterogaster scaurus",
    "snamn": "Saknar svenskt namn",
    "matsvamp": 0,
    "total_presence": 3,
    "Artfakta": "Information saknas",
    "RL2020kat": "0",
    "Svamp-grupp": "0",
    "Svamp-Undersvamp-grupp": "0",
    "SIGNAL_art": "0",
    "Svampguiden": "0",
    "Nya svamp-boken": "0",
    "Genus": "Thaxterogaster",
    "sample_plot_count": 1,
    "sample_env_count": 5,
    "Svamp-grupp-släkte": "Saknas"
  },
  {
    "SpeciesCode": "SI18-78",
    "taxon": "Cortinarius semisanguineus",
    "snamn": "rödskivig kanelspindling",
    "matsvamp": 0,
    "total_presence": 4,
    "Artfakta": "https://artfakta.se/artinformation/taxa/3718/detaljer",
    "RL2020kat": "LC",
    "Svamp-grupp": "hattsvamp",
    "Svamp-Undersvamp-grupp": "0",
    "SIGNAL_art": "0",
    "Svampguiden": "0",
    "Nya svamp-boken": "0",
    "Genus": "Cortinarius",
    "sample_plot_count": 1,
    "sample_env_count": 5,
    "Svamp-grupp-släkte": "hattsvamp"
  },
  {
    "SpeciesCode": "SI18-89",
    "taxon": "Atheliaceae sp.3",
    "snamn": "Saknar svenskt namn",
    "matsvamp": 0,
    "total_presence": 1,
    "Artfakta": "Information saknas",
    "RL2020kat": "0",
    "Svamp-grupp": "0",
    "Svamp-Undersvamp-grupp": "0",
    "SIGNAL_art": "0",
    "Svampguiden": "0",
    "Nya svamp-boken": "0",
    "Genus": "Information saknas",
    "sample_plot_count": 1,
    "sample_env_count": 5,
    "Svamp-grupp-släkte": "Saknas"
  },
  {
    "SpeciesCode": "SI18-9",
    "taxon": "Suillus variegatus",
    "snamn": "sandsopp",
    "matsvamp": 1,
    "total_presence": 2,
    "Artfakta": "https://artfakta.se/artinformation/taxa/6090/detaljer",
    "RL2020kat": "LC",
    "Svamp-grupp": "sopp",
    "Svamp-Undersvamp-grupp": "0",
    "SIGNAL_art": "0",
    "Svampguiden": "https://svampguiden.com/art/visa/suillus_variegatus",
    "Nya svamp-boken": "x",
    "Genus": "Suillus",
    "sample_plot_count": 1,
    "sample_env_count": 5,
    "Svamp-grupp-släkte": "sopp"
  },
  {
    "SpeciesCode": "SI18-998",
    "taxon": "Sistotrema alboluteum (coll.) sp.2",
    "snamn": "Saknar svenskt namn",
    "matsvamp": 0,
    "total_presence": 1,
    "Artfakta": "Information saknas",
    "RL2020kat": "0",
    "Svamp-grupp": "0",
    "Svamp-Undersvamp-grupp": "0",
    "SIGNAL_art": "0",
    "Svampguiden": "0",
    "Nya svamp-boken": "0",
    "Genus": "Sistotrema",
    "sample_plot_count": 1,
    "sample_env_count": 5,
    "Svamp-grupp-släkte": "övrigt"
  },
  {
    "SpeciesCode": "SI21-1839",
    "taxon": "Boletus pinophilus",
    "snamn": "rödbrun stensopp",
    "matsvamp": 1,
    "total_presence": 1,
    "Artfakta": "https://artfakta.se/artinformation/taxa/245723/detaljer",
    "RL2020kat": "LC",
    "Svamp-grupp": "sopp",
    "Svamp-Undersvamp-grupp": "0",
    "SIGNAL_art": "0",
    "Svampguiden": "https://svampguiden.com/art/visa/boletus_pinophilus",
    "Nya svamp-boken": "x",
    "Genus": "Boletus",
    "sample_plot_count": 1,
    "sample_env_count": 5,
    "Svamp-grupp-släkte": "sopp"
  },
  {
    "SpeciesCode": "SI21-1881",
    "taxon": "Cortinarius sanguineus",
    "snamn": "Saknar svenskt namn",
    "matsvamp": 0,
    "total_presence": 1,
    "Artfakta": "Information saknas",
    "RL2020kat": "0",
    "Svamp-grupp": "0",
    "Svamp-Undersvamp-grupp": "0",
    "SIGNAL_art": "0",
    "Svampguiden": "0",
    "Nya svamp-boken": "0",
    "Genus": "Cortinarius",
    "sample_plot_count": 1,
    "sample_env_count": 5,
    "Svamp-grupp-släkte": "hattsvamp"
  }
]