[{"taxon":"Piloderma olivaceum","snamn":"mörkt ullskinn","matsvamp":0,"total_presence":42},{"taxon":"Suillus variegatus","snamn":"sandsopp","matsvamp":1,"total_presence":41},{"taxon":"Cortinarius armillatus","snamn":"rödbandad spindling","matsvamp":0,"total_presence":20},{"taxon":"Tylospora fibrillosa","snamn":"bomullsskinn","matsvamp":0,"total_presence":8},{"taxon":"Cortinarius aff. acutus","snamn":"spetsspindling","matsvamp":0,"total_presence":7},{"taxon":"Piloderma sphaerosporum","snamn":null,"matsvamp":0,"total_presence":6},{"taxon":"Russula paludosa","snamn":"storkremla","matsvamp":1,"total_presence":5},{"taxon":"Cortinarius biformis","snamn":"gycklarspindling","matsvamp":0,"total_presence":1},{"taxon":"Piloderma byssinum","snamn":"ullskinn","matsvamp":0,"total_presence":1},{"taxon":"Thelephora terrestris","snamn":"vårtöra","matsvamp":0,"total_presence":1}]