[
  {
    "SpeciesCode": "SI18-4",
    "taxon": "Cenococcum geophilum (coll.) sp.3",
    "snamn": "Saknar svenskt namn",
    "matsvamp": 0,
    "total_presence": 86,
    "Artfakta": "Information saknas",
    "RL2020kat": "0",
    "Svamp-grupp": "0",
    "Svamp-Undersvamp-grupp": "0",
    "SIGNAL_art": "0",
    "Svampguiden": "0",
    "Nya svamp-boken": "0",
    "Genus": "Cenococcum",
    "sample_plot_count": 1,
    "sample_env_count": 1
  },
  {
    "SpeciesCode": "SI18-283",
    "taxon": "Cortinarius aff. obtusus sp.3",
    "snamn": "Saknar svenskt namn",
    "matsvamp": 0,
    "total_presence": 2,
    "Artfakta": "Information saknas",
    "RL2020kat": "0",
    "Svamp-grupp": "0",
    "Svamp-Undersvamp-grupp": "0",
    "SIGNAL_art": "0",
    "Svampguiden": "0",
    "Nya svamp-boken": "0",
    "Genus": "Cortinarius",
    "sample_plot_count": 1,
    "sample_env_count": 1
  },
  {
    "SpeciesCode": "SI18-54",
    "taxon": "Cortinarius armillatus",
    "snamn": "rödbandad spindling",
    "matsvamp": 0,
    "total_presence": 9,
    "Artfakta": "https://artfakta.se/artinformation/taxa/3541/detaljer",
    "RL2020kat": "LC",
    "Svamp-grupp": "hattsvamp",
    "Svamp-Undersvamp-grupp": "0",
    "SIGNAL_art": "0",
    "Svampguiden": "0",
    "Nya svamp-boken": "0",
    "Genus": "Cortinarius",
    "sample_plot_count": 1,
    "sample_env_count": 1
  },
  {
    "SpeciesCode": "SI18-727",
    "taxon": "Cortinarius balaustinus",
    "snamn": "strålspindling",
    "matsvamp": 0,
    "total_presence": 6,
    "Artfakta": "https://artfakta.se/artinformation/taxa/3548/detaljer",
    "RL2020kat": "LC",
    "Svamp-grupp": "hattsvamp",
    "Svamp-Undersvamp-grupp": "0",
    "SIGNAL_art": "0",
    "Svampguiden": "0",
    "Nya svamp-boken": "0",
    "Genus": "Cortinarius",
    "sample_plot_count": 1,
    "sample_env_count": 1
  },
  {
    "SpeciesCode": "SI18-520",
    "taxon": "Cortinarius casimiri",
    "snamn": "storsporig spindling",
    "matsvamp": 0,
    "total_presence": 3,
    "Artfakta": "https://artfakta.se/artinformation/taxa/3577/detaljer",
    "RL2020kat": "LC",
    "Svamp-grupp": "hattsvamp",
    "Svamp-Undersvamp-grupp": "0",
    "SIGNAL_art": "0",
    "Svampguiden": "0",
    "Nya svamp-boken": "0",
    "Genus": "Cortinarius",
    "sample_plot_count": 1,
    "sample_env_count": 1
  },
  {
    "SpeciesCode": "SI18-496",
    "taxon": "Cortinarius leucophanes",
    "snamn": "gräddspindling",
    "matsvamp": 0,
    "total_presence": 1,
    "Artfakta": "https://artfakta.se/artinformation/taxa/3651/detaljer",
    "RL2020kat": "LC",
    "Svamp-grupp": "hattsvamp",
    "Svamp-Undersvamp-grupp": "0",
    "SIGNAL_art": "0",
    "Svampguiden": "0",
    "Nya svamp-boken": "0",
    "Genus": "Cortinarius",
    "sample_plot_count": 1,
    "sample_env_count": 1
  },
  {
    "SpeciesCode": "SI18-78",
    "taxon": "Cortinarius semisanguineus",
    "snamn": "rödskivig kanelspindling",
    "matsvamp": 0,
    "total_presence": 1,
    "Artfakta": "https://artfakta.se/artinformation/taxa/3718/detaljer",
    "RL2020kat": "LC",
    "Svamp-grupp": "hattsvamp",
    "Svamp-Undersvamp-grupp": "0",
    "SIGNAL_art": "0",
    "Svampguiden": "0",
    "Nya svamp-boken": "0",
    "Genus": "Cortinarius",
    "sample_plot_count": 1,
    "sample_env_count": 1
  },
  {
    "SpeciesCode": "SI18-593",
    "taxon": "Cortinarius sp.8",
    "snamn": "Saknar svenskt namn",
    "matsvamp": 0,
    "total_presence": 1,
    "Artfakta": "Information saknas",
    "RL2020kat": "0",
    "Svamp-grupp": "0",
    "Svamp-Undersvamp-grupp": "0",
    "SIGNAL_art": "0",
    "Svampguiden": "0",
    "Nya svamp-boken": "0",
    "Genus": "Cortinarius",
    "sample_plot_count": 1,
    "sample_env_count": 1
  },
  {
    "SpeciesCode": "SI18-1609",
    "taxon": "Craterellus tubaeformis",
    "snamn": "trattkantarell",
    "matsvamp": 1,
    "total_presence": 1,
    "Artfakta": "https://artfakta.se/artinformation/taxa/3217/detaljer",
    "RL2020kat": "LC",
    "Svamp-grupp": "kantarell",
    "Svamp-Undersvamp-grupp": "0",
    "SIGNAL_art": "0",
    "Svampguiden": "https://svampguiden.com/art/visa/cantharellus_tubaeformis",
    "Nya svamp-boken": "x",
    "Genus": "Craterellus",
    "sample_plot_count": 1,
    "sample_env_count": 1
  },
  {
    "SpeciesCode": "SI18-26",
    "taxon": "Hyaloscypha finlandica sp.1",
    "snamn": "Saknar svenskt namn",
    "matsvamp": 0,
    "total_presence": 2,
    "Artfakta": "Information saknas",
    "RL2020kat": "0",
    "Svamp-grupp": "0",
    "Svamp-Undersvamp-grupp": "0",
    "SIGNAL_art": "0",
    "Svampguiden": "0",
    "Nya svamp-boken": "0",
    "Genus": "Hyaloscypha",
    "sample_plot_count": 1,
    "sample_env_count": 1
  },
  {
    "SpeciesCode": "SI18-304",
    "taxon": "Hyaloscypha vraolstadiae sp.1",
    "snamn": "Saknar svenskt namn",
    "matsvamp": 0,
    "total_presence": 1,
    "Artfakta": "Information saknas",
    "RL2020kat": "0",
    "Svamp-grupp": "0",
    "Svamp-Undersvamp-grupp": "0",
    "SIGNAL_art": "0",
    "Svampguiden": "0",
    "Nya svamp-boken": "0",
    "Genus": "Hyaloscypha",
    "sample_plot_count": 1,
    "sample_env_count": 1
  },
  {
    "SpeciesCode": "SI18-444",
    "taxon": "Lactarius ciliatus",
    "snamn": "Saknar svenskt namn",
    "matsvamp": 0,
    "total_presence": 1,
    "Artfakta": "Information saknas",
    "RL2020kat": "0",
    "Svamp-grupp": "0",
    "Svamp-Undersvamp-grupp": "0",
    "SIGNAL_art": "0",
    "Svampguiden": "0",
    "Nya svamp-boken": "0",
    "Genus": "Lactarius",
    "sample_plot_count": 1,
    "sample_env_count": 1
  },
  {
    "SpeciesCode": "SI18-101",
    "taxon": "Lactarius tabidus",
    "snamn": "småriska",
    "matsvamp": 0,
    "total_presence": 4,
    "Artfakta": "https://artfakta.se/artinformation/taxa/236531/detaljer",
    "RL2020kat": "LC",
    "Svamp-grupp": "hattsvamp",
    "Svamp-Undersvamp-grupp": "0",
    "SIGNAL_art": "0",
    "Svampguiden": "0",
    "Nya svamp-boken": "0",
    "Genus": "Lactarius",
    "sample_plot_count": 1,
    "sample_env_count": 1
  },
  {
    "SpeciesCode": "SI18-831",
    "taxon": "Leccinum sp.1",
    "snamn": "Saknar svenskt namn",
    "matsvamp": 0,
    "total_presence": 2,
    "Artfakta": "Information saknas",
    "RL2020kat": "0",
    "Svamp-grupp": "0",
    "Svamp-Undersvamp-grupp": "0",
    "SIGNAL_art": "0",
    "Svampguiden": "0",
    "Nya svamp-boken": "0",
    "Genus": "Leccinum",
    "sample_plot_count": 1,
    "sample_env_count": 1
  },
  {
    "SpeciesCode": "SI18-90",
    "taxon": "Polyozellus umbrinus",
    "snamn": "Saknar svenskt namn",
    "matsvamp": 0,
    "total_presence": 9,
    "Artfakta": "https://artfakta.se/artinformation/taxa/6040133/detaljer",
    "RL2020kat": "LC",
    "Svamp-grupp": "skinnsvamp",
    "Svamp-Undersvamp-grupp": "0",
    "SIGNAL_art": "0",
    "Svampguiden": "0",
    "Nya svamp-boken": "0",
    "Genus": "Polyozellus",
    "sample_plot_count": 1,
    "sample_env_count": 1
  },
  {
    "SpeciesCode": "SI18-227",
    "taxon": "Russula aquosa",
    "snamn": "sumpkremla",
    "matsvamp": 0,
    "total_presence": 1,
    "Artfakta": "https://artfakta.se/artinformation/taxa/5832/detaljer",
    "RL2020kat": "LC",
    "Svamp-grupp": "hattsvamp",
    "Svamp-Undersvamp-grupp": "0",
    "SIGNAL_art": "0",
    "Svampguiden": "0",
    "Nya svamp-boken": "0",
    "Genus": "Russula",
    "sample_plot_count": 1,
    "sample_env_count": 1
  },
  {
    "SpeciesCode": "SI18-626",
    "taxon": "Russula gracillima",
    "snamn": "spädkremla",
    "matsvamp": 0,
    "total_presence": 2,
    "Artfakta": "https://artfakta.se/artinformation/taxa/5870/detaljer",
    "RL2020kat": "LC",
    "Svamp-grupp": "hattsvamp",
    "Svamp-Undersvamp-grupp": "0",
    "SIGNAL_art": "0",
    "Svampguiden": "0",
    "Nya svamp-boken": "0",
    "Genus": "Russula",
    "sample_plot_count": 1,
    "sample_env_count": 1
  },
  {
    "SpeciesCode": "SI18-302",
    "taxon": "Russula versicolor",
    "snamn": "skarp sienakremla",
    "matsvamp": 0,
    "total_presence": 2,
    "Artfakta": "https://artfakta.se/artinformation/taxa/5942/detaljer",
    "RL2020kat": "LC",
    "Svamp-grupp": "hattsvamp",
    "Svamp-Undersvamp-grupp": "0",
    "SIGNAL_art": "0",
    "Svampguiden": "0",
    "Nya svamp-boken": "0",
    "Genus": "Russula",
    "sample_plot_count": 1,
    "sample_env_count": 1
  },
  {
    "SpeciesCode": "SI18-10",
    "taxon": "Tylospora fibrillosa",
    "snamn": "bomullsskinn",
    "matsvamp": 0,
    "total_presence": 1,
    "Artfakta": "https://artfakta.se/artinformation/taxa/6347/detaljer",
    "RL2020kat": "LC",
    "Svamp-grupp": "skinnsvamp",
    "Svamp-Undersvamp-grupp": "0",
    "SIGNAL_art": "0",
    "Svampguiden": "0",
    "Nya svamp-boken": "0",
    "Genus": "Tylospora",
    "sample_plot_count": 1,
    "sample_env_count": 1
  }
]