[{"taxon":"Tomentella sp. 19","snamn":"filtskinn","matsvamp":0,"total_presence":42,"Artfakta":"Information saknas","RL2020kat":"0","Svamp-grupp":"0","Svamp-Undersvamp-grupp":"0","Signal_art":"0","Svampguiden":"0"},{"taxon":"Trichophaea sp. 1","snamn":"Saknar svenskt namn","matsvamp":0,"total_presence":35,"Artfakta":"Information saknas","RL2020kat":"0","Svamp-grupp":"0","Svamp-Undersvamp-grupp":"0","Signal_art":"0","Svampguiden":"0"},{"taxon":"Amphinema byssoides","snamn":"kraterskinn","matsvamp":0,"total_presence":33,"Artfakta":"https://artfakta.se/artinformation/taxa/2991/detaljer","RL2020kat":"LC","Svamp-grupp":"skinnsvamp","Svamp-Undersvamp-grupp":"0","Signal_art":"0","Svampguiden":"0"},{"taxon":"Tomentella sp. 21","snamn":"filtskinn","matsvamp":0,"total_presence":21,"Artfakta":"Information saknas","RL2020kat":"0","Svamp-grupp":"0","Svamp-Undersvamp-grupp":"0","Signal_art":"0","Svampguiden":"0"},{"taxon":"Inocybe curvipes","snamn":"sommartråding","matsvamp":0,"total_presence":8,"Artfakta":"https://artfakta.se/artinformation/taxa/4575/detaljer","RL2020kat":"LC","Svamp-grupp":"hattsvamp","Svamp-Undersvamp-grupp":"0","Signal_art":"0","Svampguiden":"0"},{"taxon":"Serendipita sp. 11","snamn":"Saknar svenskt namn","matsvamp":0,"total_presence":8,"Artfakta":"Information saknas","RL2020kat":"0","Svamp-grupp":"0","Svamp-Undersvamp-grupp":"0","Signal_art":"0","Svampguiden":"0"},{"taxon":"Inocybe proximella","snamn":"Saknar svenskt namn","matsvamp":0,"total_presence":6,"Artfakta":"https://artfakta.se/artinformation/taxa/236460/detaljer","RL2020kat":"LC","Svamp-grupp":"hattsvamp","Svamp-Undersvamp-grupp":"0","Signal_art":"0","Svampguiden":"0"},{"taxon":"Piloderma bicolor","snamn":"gultrådsskinn","matsvamp":0,"total_presence":4,"Artfakta":"Information saknas","RL2020kat":"0","Svamp-grupp":"0","Svamp-Undersvamp-grupp":"0","Signal_art":"0","Svampguiden":"0"},{"taxon":"Tomentella ellisii","snamn":"Saknar svenskt namn","matsvamp":0,"total_presence":4,"Artfakta":"https://artfakta.se/artinformation/taxa/6165/detaljer","RL2020kat":"NA","Svamp-grupp":"skinnsvamp","Svamp-Undersvamp-grupp":"0","Signal_art":"0","Svampguiden":"0"},{"taxon":"Tomentella terrestris","snamn":"Saknar svenskt namn","matsvamp":0,"total_presence":4,"Artfakta":"https://artfakta.se/artinformation/taxa/6180/detaljer","RL2020kat":"NA","Svamp-grupp":"skinnsvamp","Svamp-Undersvamp-grupp":"0","Signal_art":"0","Svampguiden":"0"},{"taxon":"Hysterangium sp.","snamn":"brosktryfflar","matsvamp":0,"total_presence":1,"Artfakta":"Information saknas","RL2020kat":"0","Svamp-grupp":"0","Svamp-Undersvamp-grupp":"0","Signal_art":"0","Svampguiden":"0"},{"taxon":"Naucoria bohemica","snamn":"silverskräling","matsvamp":0,"total_presence":1,"Artfakta":"https://artfakta.se/artinformation/taxa/5200/detaljer","RL2020kat":"LC","Svamp-grupp":"hattsvamp","Svamp-Undersvamp-grupp":"0","Signal_art":"0","Svampguiden":"0"},{"taxon":"Tylospora asterophora","snamn":"astralskinn","matsvamp":0,"total_presence":1,"Artfakta":"https://artfakta.se/artinformation/taxa/6346/detaljer","RL2020kat":"LC","Svamp-grupp":"skinnsvamp","Svamp-Undersvamp-grupp":"0","Signal_art":"0","Svampguiden":"0"}]