[{"taxon":"Amphinema byssoides","snamn":"kraterskinn","matsvamp":0,"total_presence":21},{"taxon":"Piloderma olivaceum","snamn":"mörkt ullskinn","matsvamp":0,"total_presence":18},{"taxon":"Cortinarius sp. 3","snamn":"spindlingar","matsvamp":0,"total_presence":15},{"taxon":"Russula vinososordida","snamn":"falsk vinkremla","matsvamp":0,"total_presence":14},{"taxon":"Piloderma sphaerosporum","snamn":null,"matsvamp":0,"total_presence":12},{"taxon":"Russula pubescens","snamn":"lundvinkremla","matsvamp":0,"total_presence":11},{"taxon":"Cortinarius alboviolaceus","snamn":"blekviolett spindling","matsvamp":0,"total_presence":10},{"taxon":"Piloderma bicolor","snamn":"gultrådsskinn","matsvamp":0,"total_presence":10},{"taxon":"Pseudotomentella sp. 3","snamn":null,"matsvamp":0,"total_presence":8},{"taxon":"Sistotrema alboluteum","snamn":"oljeporing","matsvamp":0,"total_presence":4},{"taxon":"Amphinema sp. 1","snamn":null,"matsvamp":0,"total_presence":3},{"taxon":"Cortinarius armillatus","snamn":"rödbandad spindling","matsvamp":0,"total_presence":3},{"taxon":"Pseudotomentella tristis","snamn":null,"matsvamp":0,"total_presence":3},{"taxon":"Suillus variegatus","snamn":"sandsopp","matsvamp":1,"total_presence":2},{"taxon":"Cortinarius casimiri","snamn":"storsporig spindling","matsvamp":0,"total_presence":1},{"taxon":"Cortinarius semisanguineus","snamn":"rödskivig kanelspindling","matsvamp":0,"total_presence":1},{"taxon":"Lactarius vietus","snamn":"gråriska","matsvamp":0,"total_presence":1},{"taxon":"Russula griseascens","snamn":"grånande giftkremla","matsvamp":0,"total_presence":1}]