[
  {
    "taxon": "Piloderma olivaceum",
    "snamn": "mörkt ullskinn",
    "matsvamp": 0,
    "total_presence": 36,
    "Artfakta": "https://artfakta.se/artinformation/taxa/5548/detaljer",
    "RL2020kat": "LC",
    "Svamp-grupp": "skinnsvamp",
    "Svamp-Undersvamp-grupp": "0",
    "Signal_art": "0",
    "Svampguiden": "0",
    "sample_plot_count": 4
  },
  {
    "taxon": "Tylospora fibrillosa",
    "snamn": "bomullsskinn",
    "matsvamp": 0,
    "total_presence": 18,
    "Artfakta": "https://artfakta.se/artinformation/taxa/6347/detaljer",
    "RL2020kat": "LC",
    "Svamp-grupp": "skinnsvamp",
    "Svamp-Undersvamp-grupp": "0",
    "Signal_art": "0",
    "Svampguiden": "0",
    "sample_plot_count": 4
  },
  {
    "taxon": "Piloderma sp. 3",
    "snamn": "Saknar svenskt namn",
    "matsvamp": 0,
    "total_presence": 14,
    "Artfakta": "Information saknas",
    "RL2020kat": "0",
    "Svamp-grupp": "0",
    "Svamp-Undersvamp-grupp": "0",
    "Signal_art": "0",
    "Svampguiden": "0",
    "sample_plot_count": 4
  },
  {
    "taxon": "Piloderma sp. 4",
    "snamn": "Saknar svenskt namn",
    "matsvamp": 0,
    "total_presence": 14,
    "Artfakta": "Information saknas",
    "RL2020kat": "0",
    "Svamp-grupp": "0",
    "Svamp-Undersvamp-grupp": "0",
    "Signal_art": "0",
    "Svampguiden": "0",
    "sample_plot_count": 4
  },
  {
    "taxon": "Serendipita sp. 9",
    "snamn": "Saknar svenskt namn",
    "matsvamp": 0,
    "total_presence": 8,
    "Artfakta": "Information saknas",
    "RL2020kat": "0",
    "Svamp-grupp": "0",
    "Svamp-Undersvamp-grupp": "0",
    "Signal_art": "0",
    "Svampguiden": "0",
    "sample_plot_count": 4
  },
  {
    "taxon": "Cortinarius casimiri",
    "snamn": "storsporig spindling",
    "matsvamp": 0,
    "total_presence": 6,
    "Artfakta": "https://artfakta.se/artinformation/taxa/3577/detaljer",
    "RL2020kat": "LC",
    "Svamp-grupp": "hattsvamp",
    "Svamp-Undersvamp-grupp": "0",
    "Signal_art": "0",
    "Svampguiden": "0",
    "sample_plot_count": 4
  },
  {
    "taxon": "Suillus luteus",
    "snamn": "smörsopp",
    "matsvamp": 1,
    "total_presence": 6,
    "Artfakta": "https://artfakta.se/artinformation/taxa/6088/detaljer",
    "RL2020kat": "LC",
    "Svamp-grupp": "sopp",
    "Svamp-Undersvamp-grupp": "0",
    "Signal_art": "0",
    "Svampguiden": "https://svampguiden.com/art/visa/suillus_luteus",
    "sample_plot_count": 4
  },
  {
    "taxon": "Inocybe giacomi",
    "snamn": "Saknar svenskt namn",
    "matsvamp": 0,
    "total_presence": 2,
    "Artfakta": "Information saknas",
    "RL2020kat": "0",
    "Svamp-grupp": "0",
    "Svamp-Undersvamp-grupp": "0",
    "Signal_art": "0",
    "Svampguiden": "0",
    "sample_plot_count": 4
  },
  {
    "taxon": "Inocybe lacera",
    "snamn": "mörktråding",
    "matsvamp": 0,
    "total_presence": 2,
    "Artfakta": "https://artfakta.se/artinformation/taxa/4598/detaljer",
    "RL2020kat": "LC",
    "Svamp-grupp": "hattsvamp",
    "Svamp-Undersvamp-grupp": "0",
    "Signal_art": "0",
    "Svampguiden": "0",
    "sample_plot_count": 4
  },
  {
    "taxon": "Piloderma sphaerosporum",
    "snamn": "Saknar svenskt namn",
    "matsvamp": 0,
    "total_presence": 2,
    "Artfakta": "https://artfakta.se/artinformation/taxa/253758/detaljer",
    "RL2020kat": "LC",
    "Svamp-grupp": "skinnsvamp",
    "Svamp-Undersvamp-grupp": "0",
    "Signal_art": "0",
    "Svampguiden": "0",
    "sample_plot_count": 4
  },
  {
    "taxon": "Wilcoxina rehmii",
    "snamn": "Saknar svenskt namn",
    "matsvamp": 0,
    "total_presence": 2,
    "Artfakta": "Information saknas",
    "RL2020kat": "0",
    "Svamp-grupp": "0",
    "Svamp-Undersvamp-grupp": "0",
    "Signal_art": "0",
    "Svampguiden": "0",
    "sample_plot_count": 4
  },
  {
    "taxon": "Russula aquosa",
    "snamn": "sumpkremla",
    "matsvamp": 0,
    "total_presence": 1,
    "Artfakta": "https://artfakta.se/artinformation/taxa/5832/detaljer",
    "RL2020kat": "LC",
    "Svamp-grupp": "hattsvamp",
    "Svamp-Undersvamp-grupp": "0",
    "Signal_art": "0",
    "Svampguiden": "0",
    "sample_plot_count": 4
  },
  {
    "taxon": "Russula versicolor",
    "snamn": "skarp sienakremla",
    "matsvamp": 0,
    "total_presence": 1,
    "Artfakta": "https://artfakta.se/artinformation/taxa/5942/detaljer",
    "RL2020kat": "LC",
    "Svamp-grupp": "hattsvamp",
    "Svamp-Undersvamp-grupp": "0",
    "Signal_art": "0",
    "Svampguiden": "0",
    "sample_plot_count": 4
  },
  {
    "taxon": "Suillus variegatus",
    "snamn": "sandsopp",
    "matsvamp": 1,
    "total_presence": 1,
    "Artfakta": "https://artfakta.se/artinformation/taxa/6090/detaljer",
    "RL2020kat": "LC",
    "Svamp-grupp": "sopp",
    "Svamp-Undersvamp-grupp": "0",
    "Signal_art": "0",
    "Svampguiden": "https://svampguiden.com/art/visa/suillus_variegatus",
    "sample_plot_count": 4
  }
]
