[{"taxon":"Tomentella sp. 1","snamn":"filtskinn","matsvamp":0,"total_presence":63,"Artfakta":"Information saknas","RL2020kat":"0","Svamp-grupp":"0","Svamp-Undersvamp-grupp":"0","Signal_art":"0","Svampguiden":"0","sample_plot_count":6},{"taxon":"Thelephoraceae sp. 1","snamn":"Saknar svenskt namn","matsvamp":0,"total_presence":45,"Artfakta":"Information saknas","RL2020kat":"0","Svamp-grupp":"0","Svamp-Undersvamp-grupp":"0","Signal_art":"0","Svampguiden":"0","sample_plot_count":6},{"taxon":"Piloderma bicolor","snamn":"gultrådsskinn","matsvamp":0,"total_presence":44,"Artfakta":"Information saknas","RL2020kat":"0","Svamp-grupp":"0","Svamp-Undersvamp-grupp":"0","Signal_art":"0","Svampguiden":"0","sample_plot_count":6},{"taxon":"Tomentella sp. 4","snamn":"filtskinn","matsvamp":0,"total_presence":42,"Artfakta":"Information saknas","RL2020kat":"0","Svamp-grupp":"0","Svamp-Undersvamp-grupp":"0","Signal_art":"0","Svampguiden":"0","sample_plot_count":6},{"taxon":"Pseudotomentella sp. 3","snamn":"Saknar svenskt namn","matsvamp":0,"total_presence":40,"Artfakta":"Information saknas","RL2020kat":"0","Svamp-grupp":"0","Svamp-Undersvamp-grupp":"0","Signal_art":"0","Svampguiden":"0","sample_plot_count":6},{"taxon":"Lactarius vietus","snamn":"gråriska","matsvamp":0,"total_presence":9,"Artfakta":"https://artfakta.se/artinformation/taxa/4784/detaljer","RL2020kat":"LC","Svamp-grupp":"hattsvamp","Svamp-Undersvamp-grupp":"0","Signal_art":"0","Svampguiden":"0","sample_plot_count":6},{"taxon":"Humaria hemisphaerica","snamn":"luddskål","matsvamp":0,"total_presence":5,"Artfakta":"https://artfakta.se/artinformation/taxa/4356/detaljer","RL2020kat":"LC","Svamp-grupp":"skålsvamp","Svamp-Undersvamp-grupp":"0","Signal_art":"0","Svampguiden":"0","sample_plot_count":6},{"taxon":"Lactarius tabidus","snamn":"småriska","matsvamp":0,"total_presence":3,"Artfakta":"https://artfakta.se/artinformation/taxa/236531/detaljer","RL2020kat":"LC","Svamp-grupp":"hattsvamp","Svamp-Undersvamp-grupp":"0","Signal_art":"0","Svampguiden":"0","sample_plot_count":6},{"taxon":"Sistotrema albopallescens","snamn":"ljungporing","matsvamp":0,"total_presence":2,"Artfakta":"Information saknas","RL2020kat":"0","Svamp-grupp":"0","Svamp-Undersvamp-grupp":"0","Signal_art":"0","Svampguiden":"0","sample_plot_count":6},{"taxon":"Tomentella ellisii","snamn":"Saknar svenskt namn","matsvamp":0,"total_presence":2,"Artfakta":"https://artfakta.se/artinformation/taxa/6165/detaljer","RL2020kat":"NA","Svamp-grupp":"skinnsvamp","Svamp-Undersvamp-grupp":"0","Signal_art":"0","Svampguiden":"0","sample_plot_count":6},{"taxon":"Cortinarius betuletorum","snamn":"rättikspindling","matsvamp":0,"total_presence":1,"Artfakta":"Information saknas","RL2020kat":"0","Svamp-grupp":"0","Svamp-Undersvamp-grupp":"0","Signal_art":"0","Svampguiden":"0","sample_plot_count":6},{"taxon":"Lactarius trivialis","snamn":"skogsriska","matsvamp":0,"total_presence":1,"Artfakta":"https://artfakta.se/artinformation/taxa/4780/detaljer","RL2020kat":"LC","Svamp-grupp":"hattsvamp","Svamp-Undersvamp-grupp":"0","Signal_art":"0","Svampguiden":"https://svampguiden.com/art/visa/lactarius_trivialis","sample_plot_count":6},{"taxon":"Russula consobrina","snamn":"nässelkremla","matsvamp":0,"total_presence":1,"Artfakta":"https://artfakta.se/artinformation/taxa/5848/detaljer","RL2020kat":"LC","Svamp-grupp":"hattsvamp","Svamp-Undersvamp-grupp":"0","Signal_art":"0","Svampguiden":"0","sample_plot_count":6}]